{
  "Lockheart Indigo": "https://store.steampowered.com/app/1345470/Lockheart_Indigo/?snr=1_7_7_240_150_1",
  "Song of Farca: Prologue": "https://store.steampowered.com/app/1493020/Song_of_Farca_Prologue/?snr=1_7_7_240_150_1",
  "6 Seasons and a Game": "https://store.steampowered.com/app/1460830/6_Seasons_and_a_Game/?snr=1_7_7_240_150_1",
  "Just Act Natural": "https://store.steampowered.com/app/1485080/Just_Act_Natural/?snr=1_7_7_240_150_1",
  "Pre-Shave": "https://store.steampowered.com/app/1383270/PreShave/?snr=1_7_7_240_150_1",
  "Captain Bones: Prologue": "https://store.steampowered.com/app/1671600/Captain_Bones_Prologue/?snr=1_7_7_240_150_1",
  "Impulse, From Here!": "https://store.steampowered.com/app/1385210/Impulse_From_Here/?snr=1_7_7_240_150_1",
  "Vectromirror 0™": "https://store.steampowered.com/app/1296560/Vectromirror_0/?snr=1_7_7_240_150_1",
  "Don Flatus: Poop Hunter": "https://store.steampowered.com/app/1314480/Don_Flatus_Poop_Hunter/?snr=1_7_7_240_150_1",
  "Adventure Craft": "https://store.steampowered.com/app/624890/Adventure_Craft/?snr=1_7_7_240_150_1",
  "Fadeout: Underground": "https://store.steampowered.com/app/1306570/Fadeout_Underground/?snr=1_7_7_240_150_1",
  "Ghosty": "https://store.steampowered.com/app/1390060/Ghosty/?snr=1_7_7_240_150_1",
  "The Struggles Of Stefan": "https://store.steampowered.com/app/1382020/The_Struggles_Of_Stefan/?snr=1_7_7_240_150_1",
  "The Last Show of Mr. Chardish: Act I": "https://store.steampowered.com/app/1397140/The_Last_Show_of_Mr_Chardish_Act_I/?snr=1_7_7_240_150_1",
  "Welcome to Emba": "https://store.steampowered.com/app/1433190/Welcome_to_Emba/?snr=1_7_7_240_150_1",
  "Franky the Bumwalker: REBORN": "https://store.steampowered.com/app/1418470/Franky_the_Bumwalker_REBORN/?snr=1_7_7_240_150_1",
  "Super Nate Adventure": "https://store.steampowered.com/app/1370250/Super_Nate_Adventure/?snr=1_7_7_240_150_1",
  "Aurora": "https://store.steampowered.com/app/1382380/Aurora/?snr=1_7_7_240_150_1",
  "WOMG Lite version": "https://store.steampowered.com/app/1444420/WOMG_Lite_version/?snr=1_7_7_240_150_1",
  "Six Paths": "https://store.steampowered.com/app/1375460/Six_Paths/?snr=1_7_7_240_150_1",
  "Cyberforge: First Light": "https://store.steampowered.com/app/1437980/Cyberforge_First_Light/?snr=1_7_7_240_150_1",
  "Eye of the Beholder": "https://store.steampowered.com/app/1425330/Eye_of_the_Beholder/?snr=1_7_7_240_150_1",
  "Alpha &amp; Beta": "https://store.steampowered.com/app/968320/Alpha__Beta/?snr=1_7_7_240_150_1",
  "Postponed": "https://store.steampowered.com/app/3096730/Postponed/?snr=1_7_7_240_150_1",
  "Streets Ablaze": "https://store.steampowered.com/app/792500/Streets_Ablaze/?snr=1_7_7_240_150_1",
  "GranAge": "https://store.steampowered.com/app/1412470/GranAge/?snr=1_7_7_240_150_1",
  "I Am Jesus Christ: Prologue": "https://store.steampowered.com/app/1509650/I_Am_Jesus_Christ_Prologue/?snr=1_7_7_240_150_1",
  "Iron League": "https://store.steampowered.com/app/771060/Iron_League/?snr=1_7_7_240_150_1",
  "Go All Out: Free To Play": "https://store.steampowered.com/app/1150040/Go_All_Out_Free_To_Play/?snr=1_7_7_240_150_1",
  "Linx Battle Arena": "https://store.steampowered.com/app/697370/Linx_Battle_Arena/?snr=1_7_7_240_150_1",
  "Soulworker": "https://store.steampowered.com/app/1377580/Soulworker/?snr=1_7_7_240_150_1",
  "SMASH LEGENDS": "https://store.steampowered.com/app/1352080/SMASH_LEGENDS/?snr=1_7_7_240_150_1",
  "The Fall of Eskaria": "https://store.steampowered.com/app/1339530/The_Fall_of_Eskaria/?snr=1_7_7_240_150_1",
  "Clown2Beat": "https://store.steampowered.com/app/547870/Clown2Beat/?snr=1_7_7_240_150_1",
  "KurtzPel": "https://store.steampowered.com/app/844870/KurtzPel/?snr=1_7_7_240_150_1",
  "NightShift": "https://store.steampowered.com/app/1484340/NightShift/?snr=1_7_7_240_150_1",
  "Hippocampus": "https://store.steampowered.com/app/1079940/Hippocampus/?snr=1_7_7_240_150_1",
  "The Panic Room. House of secrets": "https://store.steampowered.com/app/436160/The_Panic_Room_House_of_secrets/?snr=1_7_7_240_150_1",
  "CosmicBreak Universal": "https://store.steampowered.com/app/1140620/CosmicBreak_Universal/?snr=1_7_7_240_150_1",
  "Turtle's Quest": "https://store.steampowered.com/app/708990/Turtles_Quest/?snr=1_7_7_240_150_1",
  "Legends Of Iona RPG (2007 arcade mod)": "https://store.steampowered.com/app/668730/Legends_Of_Iona_RPG_2007_arcade_mod/?snr=1_7_7_240_150_1",
  "Keepers of the Trees": "https://store.steampowered.com/app/1356800/Keepers_of_the_Trees/?snr=1_7_7_240_150_1",
  "Kingshunt": "https://store.steampowered.com/app/922620/Kingshunt/?snr=1_7_7_240_150_1",
  "True Reporter. Mystery of Mistwood": "https://store.steampowered.com/app/2682300/True_Reporter_Mystery_of_Mistwood/?snr=1_7_7_240_150_1",
  "GHOSTWINTER": "https://store.steampowered.com/app/1470060/GHOSTWINTER/?snr=1_7_7_240_150_1",
  "Blackstorm": "https://store.steampowered.com/app/1315240/Blackstorm/?snr=1_7_7_240_150_1"
}