{
  "Homicipher: Prologue": "https://store.steampowered.com/app/2423320/Homicipher_Prologue/?snr=1_7_7_240_150_1",
  "BLACK BOX LSS - The Shining Immortal": "https://store.steampowered.com/app/2434340/BLACK_BOX_LSS__The_Shining_Immortal/?snr=1_7_7_240_150_1",
  "Our Life: Beginnings &amp; Always": "https://store.steampowered.com/app/1129190/Our_Life_Beginnings__Always/?snr=1_7_7_240_150_1",
  "A Date with Death": "https://store.steampowered.com/app/2415010/A_Date_with_Death/?snr=1_7_7_240_150_1",
  "Helltaker": "https://store.steampowered.com/app/1289310/Helltaker/?snr=1_7_7_240_150_1",
  "Star Fetchers": "https://store.steampowered.com/app/1178030/Star_Fetchers/?snr=1_7_7_240_150_1",
  "REFLEXIA Prototype ver.": "https://store.steampowered.com/app/1997680/REFLEXIA_Prototype_ver/?snr=1_7_7_240_150_1",
  "MetaWare High School (Demo)": "https://store.steampowered.com/app/1194740/MetaWare_High_School_Demo/?snr=1_7_7_240_150_1",
  "Doki Doki Literature Club!": "https://store.steampowered.com/app/698780/Doki_Doki_Literature_Club/?snr=1_7_7_240_150_1",
  "Cinderella Phenomenon - Otome/Visual Novel": "https://store.steampowered.com/app/568770/Cinderella_Phenomenon__OtomeVisual_Novel/?snr=1_7_7_240_150_1",
  "Everlasting Summer": "https://store.steampowered.com/app/331470/Everlasting_Summer/?snr=1_7_7_240_150_1",
  "There is No GreenDam": "https://store.steampowered.com/app/1109460/There_is_No_GreenDam/?snr=1_7_7_240_150_1",
  "Tailor Tales": "https://store.steampowered.com/app/939330/Tailor_Tales/?snr=1_7_7_240_150_1",
  "Grey Instinct": "https://store.steampowered.com/app/1570960/Grey_Instinct/?snr=1_7_7_240_150_1",
  "First Snow": "https://store.steampowered.com/app/1259430/First_Snow/?snr=1_7_7_240_150_1",
  "Yog-Sothoth's Yard - Official Picture Package": "https://store.steampowered.com/app/2699860/YogSothoths_Yard__Official_Picture_Package/?snr=1_7_7_240_150_1",
  "Graveyard Girls": "https://store.steampowered.com/app/2055540/Graveyard_Girls/?snr=1_7_7_240_150_1",
  "Love Alone Death": "https://store.steampowered.com/app/2627030/Love_Alone_Death/?snr=1_7_7_240_150_1",
  "Emberfate: Tempest of Elements": "https://store.steampowered.com/app/2164490/Emberfate_Tempest_of_Elements/?snr=1_7_7_240_150_1",
  "Pair-a-Site": "https://store.steampowered.com/app/1228430/PairaSite/?snr=1_7_7_240_150_1",
  "That's Not How it Happened": "https://store.steampowered.com/app/1958400/Thats_Not_How_it_Happened/?snr=1_7_7_240_150_1",
  "Life After Magic": "https://store.steampowered.com/app/2332130/Life_After_Magic/?snr=1_7_7_240_150_1",
  "The Day We Met was a Regular Day in the Infinitely Looping Highschool, is That Normal?": "https://store.steampowered.com/app/1907180/The_Day_We_Met_was_a_Regular_Day_in_the_Infinitely_Looping_Highschool_is_That_Normal/?snr=1_7_7_240_150_1",
  "Sucker for Love: Prelude": "https://store.steampowered.com/app/1820740/Sucker_for_Love_Prelude/?snr=1_7_7_240_150_1",
  "Ballads at Midnight": "https://store.steampowered.com/app/1967870/Ballads_at_Midnight/?snr=1_7_7_240_150_1",
  "Memoir": "https://store.steampowered.com/app/1985250/Memoir/?snr=1_7_7_240_150_1",
  "Curtain Call": "https://store.steampowered.com/app/1839180/Curtain_Call/?snr=1_7_7_240_150_1",
  "Börd Killer": "https://store.steampowered.com/app/2370660/Brd_Killer/?snr=1_7_7_240_150_1",
  "ERROR143": "https://store.steampowered.com/app/2066550/ERROR143/?snr=1_7_7_240_150_1",
  "Brief Karate Foolish": "https://store.steampowered.com/app/546390/Brief_Karate_Foolish/?snr=1_7_7_240_150_1",
  "Danganronpa V3: Killing Harmony Demo Ver.": "https://store.steampowered.com/app/589120/Danganronpa_V3_Killing_Harmony_Demo_Ver/?snr=1_7_7_240_150_1",
  "Confess My Love": "https://store.steampowered.com/app/637850/Confess_My_Love/?snr=1_7_7_240_150_1",
  "Lovers of Aether": "https://store.steampowered.com/app/1043180/Lovers_of_Aether/?snr=1_7_7_240_150_1",
  "//TODO: today": "https://store.steampowered.com/app/1259240/TODO_today/?snr=1_7_7_240_150_1",
  "Midnight Witch": "https://store.steampowered.com/app/2336180/Midnight_Witch/?snr=1_7_7_240_150_1",
  "Pandemic Love": "https://store.steampowered.com/app/1558900/Pandemic_Love/?snr=1_7_7_240_150_1",
  "Mission: It's Complicated": "https://store.steampowered.com/app/1041210/Mission_Its_Complicated/?snr=1_7_7_240_150_1",
  "家有大貓 Nekojishi": "https://store.steampowered.com/app/570840/_Nekojishi/?snr=1_7_7_240_150_1",
  "Love Thyself - A Horatio Story": "https://store.steampowered.com/app/949060/Love_Thyself__A_Horatio_Story/?snr=1_7_7_240_150_1",
  "Witches x Warlocks": "https://store.steampowered.com/app/1422380/Witches_x_Warlocks/?snr=1_7_7_240_150_1",
  "Dark Nights": "https://store.steampowered.com/app/2143340/Dark_Nights/?snr=1_7_7_240_150_1",
  "a completely normal dating simulation that is definitely completely sweet, innnocent and normal: SOMETHINGETH ANIVERSARY EDITION": "https://store.steampowered.com/app/1367490/a_completely_normal_dating_simulation_that_is_definitely_completely_sweet_innnocent_and_normal_SOMETHINGETH_ANIVERSARY_EDITION/?snr=1_7_7_240_150_1",
  "Deliver Us From Evil (DUFE)": "https://store.steampowered.com/app/1674240/Deliver_Us_From_Evil_DUFE/?snr=1_7_7_240_150_1",
  "I Love You, Colonel Sanders! A Finger Lickin’ Good Dating Simulator": "https://store.steampowered.com/app/1121910/I_Love_You_Colonel_Sanders_A_Finger_Lickin_Good_Dating_Simulator/?snr=1_7_7_240_150_1",
  "Obama Maze": "https://store.steampowered.com/app/1808060/Obama_Maze/?snr=1_7_7_240_150_1",
  "Sounds of Her Love": "https://store.steampowered.com/app/603880/Sounds_of_Her_Love/?snr=1_7_7_240_150_1",
  "Heart Fragment": "https://store.steampowered.com/app/1253880/Heart_Fragment/?snr=1_7_7_240_150_1",
  "Infinite Stars - The Visual Novel": "https://store.steampowered.com/app/1716360/Infinite_Stars__The_Visual_Novel/?snr=1_7_7_240_150_1",
  "Superstorm Melon Date": "https://store.steampowered.com/app/1509830/Superstorm_Melon_Date/?snr=1_7_7_240_150_1",
  "Frosty Kiss": "https://store.steampowered.com/app/431540/Frosty_Kiss/?snr=1_7_7_240_150_1"
}