{
  "Quest for the Golden Candelabra": "https://store.steampowered.com/app/2381160/Quest_for_the_Golden_Candelabra/?snr=1_7_7_240_150_1",
  "Fishards": "https://store.steampowered.com/app/1637140/Fishards/?snr=1_7_7_240_150_1",
  "HoverRace": "https://store.steampowered.com/app/1862020/HoverRace/?snr=1_7_7_240_150_1",
  "Elewar: Fused Survivors": "https://store.steampowered.com/app/2489560/Elewar_Fused_Survivors/?snr=1_7_7_240_150_1",
  "Ruins Of Mitriom": "https://store.steampowered.com/app/1847390/Ruins_Of_Mitriom/?snr=1_7_7_240_150_1",
  "Alien Swarm: Reactive Drop": "https://store.steampowered.com/app/563560/Alien_Swarm_Reactive_Drop/?snr=1_7_7_240_150_1",
  "RUNGORE: Beginner Experience": "https://store.steampowered.com/app/2113050/RUNGORE_Beginner_Experience/?snr=1_7_7_240_150_1",
  "Undead World": "https://store.steampowered.com/app/2193420/Undead_World/?snr=1_7_7_240_150_1",
  "Slipstream: Rogue Space": "https://store.steampowered.com/app/2765860/Slipstream_Rogue_Space/?snr=1_7_7_240_150_1",
  "Yerr Out": "https://store.steampowered.com/app/1963360/Yerr_Out/?snr=1_7_7_240_150_1",
  "Wizzerd Quest": "https://store.steampowered.com/app/2785800/Wizzerd_Quest/?snr=1_7_7_240_150_1",
  "Guild Wars 2": "https://store.steampowered.com/app/1284210/Guild_Wars_2/?snr=1_7_7_240_150_1",
  "Fortress Forever": "https://store.steampowered.com/app/253530/Fortress_Forever/?snr=1_7_7_240_150_1",
  "Ultimechs": "https://store.steampowered.com/app/1657780/Ultimechs/?snr=1_7_7_240_150_1",
  "The Two of Us": "https://store.steampowered.com/app/1820170/The_Two_of_Us/?snr=1_7_7_240_150_1",
  "Empires Mod": "https://store.steampowered.com/app/17740/Empires_Mod/?snr=1_7_7_240_150_1",
  "Object N": "https://store.steampowered.com/app/1508030/Object_N/?snr=1_7_7_240_150_1",
  "OneBit Adventure": "https://store.steampowered.com/app/1688320/OneBit_Adventure/?snr=1_7_7_240_150_1",
  "Kakele Online - MMORPG": "https://store.steampowered.com/app/1541020/Kakele_Online__MMORPG/?snr=1_7_7_240_150_1",
  "Dinogen Online": "https://store.steampowered.com/app/2152990/Dinogen_Online/?snr=1_7_7_240_150_1",
  "Green New Deal Simulator": "https://store.steampowered.com/app/2334990/Green_New_Deal_Simulator/?snr=1_7_7_240_150_1",
  "Pirate101": "https://store.steampowered.com/app/620620/Pirate101/?snr=1_7_7_240_150_1",
  "Kingdom Draw": "https://store.steampowered.com/app/1986040/Kingdom_Draw/?snr=1_7_7_240_150_1",
  "GPRO - Classic racing manager": "https://store.steampowered.com/app/2169220/GPRO__Classic_racing_manager/?snr=1_7_7_240_150_1",
  "Dirty Bomb®": "https://store.steampowered.com/app/333930/Dirty_Bomb/?snr=1_7_7_240_150_1",
  "Legend of Edda: Pegasus": "https://store.steampowered.com/app/2241570/Legend_of_Edda_Pegasus/?snr=1_7_7_240_150_1",
  "Viral Firar": "https://store.steampowered.com/app/1731870/Viral_Firar/?snr=1_7_7_240_150_1",
  "Flipped": "https://store.steampowered.com/app/1835090/Flipped/?snr=1_7_7_240_150_1",
  "SCUFF(ED)": "https://store.steampowered.com/app/2083450/SCUFFED/?snr=1_7_7_240_150_1",
  "The Specter Chronicles: Episode 1 - The False Prophet": "https://store.steampowered.com/app/2243880/The_Specter_Chronicles_Episode_1__The_False_Prophet/?snr=1_7_7_240_150_1",
  "God of the Arena Dungeon": "https://store.steampowered.com/app/1571880/God_of_the_Arena_Dungeon/?snr=1_7_7_240_150_1",
  "NOVA CORE CHAOS": "https://store.steampowered.com/app/2738480/NOVA_CORE_CHAOS/?snr=1_7_7_240_150_1",
  "The Accursed Crown of the Giant King": "https://store.steampowered.com/app/1970780/The_Accursed_Crown_of_the_Giant_King/?snr=1_7_7_240_150_1",
  "Aphelion Headhunters": "https://store.steampowered.com/app/2372440/Aphelion_Headhunters/?snr=1_7_7_240_150_1",
  "Stream Arenas": "https://store.steampowered.com/app/1390300/Stream_Arenas/?snr=1_7_7_240_150_1",
  "The Benza RPG": "https://store.steampowered.com/app/1449370/The_Benza_RPG/?snr=1_7_7_240_150_1",
  "Loot Train": "https://store.steampowered.com/app/1721020/Loot_Train/?snr=1_7_7_240_150_1",
  "Dynarog 2": "https://store.steampowered.com/app/1740270/Dynarog_2/?snr=1_7_7_240_150_1",
  "Nectar of the Gods": "https://store.steampowered.com/app/1421410/Nectar_of_the_Gods/?snr=1_7_7_240_150_1",
  "Battle Of Zodiacs - Card Game": "https://store.steampowered.com/app/2325880/Battle_Of_Zodiacs__Card_Game/?snr=1_7_7_240_150_1",
  "Gemini: Binary Conflict": "https://store.steampowered.com/app/1293660/Gemini_Binary_Conflict/?snr=1_7_7_240_150_1",
  "Krunker": "https://store.steampowered.com/app/1408720/Krunker/?snr=1_7_7_240_150_1",
  "The Ultimatest Battle": "https://store.steampowered.com/app/669580/The_Ultimatest_Battle/?snr=1_7_7_240_150_1",
  "Ashen Empires": "https://store.steampowered.com/app/937380/Ashen_Empires/?snr=1_7_7_240_150_1",
  "Cube Conflict": "https://store.steampowered.com/app/1454700/Cube_Conflict/?snr=1_7_7_240_150_1",
  "ULTRA LMAD": "https://store.steampowered.com/app/1419510/ULTRA_LMAD/?snr=1_7_7_240_150_1",
  "Block N Load": "https://store.steampowered.com/app/299360/Block_N_Load/?snr=1_7_7_240_150_1",
  "MONOLISK": "https://store.steampowered.com/app/1454520/MONOLISK/?snr=1_7_7_240_150_1",
  "Five-Finger Gunslinger": "https://store.steampowered.com/app/1377240/FiveFinger_Gunslinger/?snr=1_7_7_240_150_1",
  "American Isekai Prologue": "https://store.steampowered.com/app/1350630/American_Isekai_Prologue/?snr=1_7_7_240_150_1"
}