{
  "Shadow Burglar": "https://store.steampowered.com/app/1881340/Shadow_Burglar/?snr=1_7_7_240_150_1",
  "Crime Scene Cleaner: Prologue": "https://store.steampowered.com/app/2540100/Crime_Scene_Cleaner_Prologue/?snr=1_7_7_240_150_1",
  "High Entropy: Challenges": "https://store.steampowered.com/app/1389630/High_Entropy_Challenges/?snr=1_7_7_240_150_1",
  "A Wholesome Game About Farming": "https://store.steampowered.com/app/1892850/A_Wholesome_Game_About_Farming/?snr=1_7_7_240_150_1",
  "Quiet is the Eyes": "https://store.steampowered.com/app/2611580/Quiet_is_the_Eyes/?snr=1_7_7_240_150_1",
  "Songs from the Iron Sea": "https://store.steampowered.com/app/2091370/Songs_from_the_Iron_Sea/?snr=1_7_7_240_150_1",
  "IronWolf: Free Non-VR Edition": "https://store.steampowered.com/app/2530670/IronWolf_Free_NonVR_Edition/?snr=1_7_7_240_150_1",
  "We're Tethered Together": "https://store.steampowered.com/app/2578110/Were_Tethered_Together/?snr=1_7_7_240_150_1",
  "Crawlspace 2": "https://store.steampowered.com/app/2258670/Crawlspace_2/?snr=1_7_7_240_150_1",
  "Your Average Bear": "https://store.steampowered.com/app/2349870/Your_Average_Bear/?snr=1_7_7_240_150_1",
  "Blood Orange: Definitive Edition": "https://store.steampowered.com/app/2655840/Blood_Orange_Definitive_Edition/?snr=1_7_7_240_150_1",
  "Apotheorasis • Lab of the Blind Gods | Prologue": "https://store.steampowered.com/app/1836310/Apotheorasis__Lab_of_the_Blind_Gods__Prologue/?snr=1_7_7_240_150_1",
  "Hello Neighbor Alpha 2": "https://store.steampowered.com/app/1092720/Hello_Neighbor_Alpha_2/?snr=1_7_7_240_150_1",
  "Hog Hunter 2021": "https://store.steampowered.com/app/1583280/Hog_Hunter_2021/?snr=1_7_7_240_150_1",
  "Three of Cards": "https://store.steampowered.com/app/1552250/Three_of_Cards/?snr=1_7_7_240_150_1",
  "Owlone in the Woods": "https://store.steampowered.com/app/1782600/Owlone_in_the_Woods/?snr=1_7_7_240_150_1",
  "Reimus Awesome Holiday": "https://store.steampowered.com/app/2137560/Reimus_Awesome_Holiday/?snr=1_7_7_240_150_1",
  "Dr. Langeskov, The Tiger, and The Terribly Cursed Emerald: A Whirlwind Heist": "https://store.steampowered.com/app/409160/Dr_Langeskov_The_Tiger_and_The_Terribly_Cursed_Emerald_A_Whirlwind_Heist/?snr=1_7_7_240_150_1",
  "Baldi's Basics Classic Remastered": "https://store.steampowered.com/app/1712830/Baldis_Basics_Classic_Remastered/?snr=1_7_7_240_150_1",
  "Intravenous 2: Mercenarism": "https://store.steampowered.com/app/2651330/Intravenous_2_Mercenarism/?snr=1_7_7_240_150_1",
  "Flicker of Hope": "https://store.steampowered.com/app/1314460/Flicker_of_Hope/?snr=1_7_7_240_150_1",
  "Zardy's Maze": "https://store.steampowered.com/app/1484800/Zardys_Maze/?snr=1_7_7_240_150_1",
  "Cat Burglar: A Tail of Purrsuit": "https://store.steampowered.com/app/760510/Cat_Burglar_A_Tail_of_Purrsuit/?snr=1_7_7_240_150_1",
  "Curse That Magic Cat!": "https://store.steampowered.com/app/1410830/Curse_That_Magic_Cat/?snr=1_7_7_240_150_1",
  "Ho-Ho-Home Invasion": "https://store.steampowered.com/app/1482830/HoHoHome_Invasion/?snr=1_7_7_240_150_1",
  "Hello Neighbor Alpha 1": "https://store.steampowered.com/app/1092710/Hello_Neighbor_Alpha_1/?snr=1_7_7_240_150_1",
  "Deus Ex: Revision": "https://store.steampowered.com/app/397550/Deus_Ex_Revision/?snr=1_7_7_240_150_1",
  "Anonymous Hacker Simulator: Prologue": "https://store.steampowered.com/app/2487070/Anonymous_Hacker_Simulator_Prologue/?snr=1_7_7_240_150_1",
  "Kill It With Fire: Ignition": "https://store.steampowered.com/app/1291500/Kill_It_With_Fire_Ignition/?snr=1_7_7_240_150_1",
  "Octodad (Student Edition)": "https://store.steampowered.com/app/2383860/Octodad_Student_Edition/?snr=1_7_7_240_150_1",
  "NEON STRUCT: Desperation Column": "https://store.steampowered.com/app/1848200/NEON_STRUCT_Desperation_Column/?snr=1_7_7_240_150_1",
  "One-armed robber": "https://store.steampowered.com/app/2551020/Onearmed_robber/?snr=1_7_7_240_150_1",
  "Hello Neighbor Pre-Alpha": "https://store.steampowered.com/app/1092700/Hello_Neighbor_PreAlpha/?snr=1_7_7_240_150_1",
  "I Won't Forget Hue": "https://store.steampowered.com/app/2236880/I_Wont_Forget_Hue/?snr=1_7_7_240_150_1",
  "Counter Agents": "https://store.steampowered.com/app/549090/Counter_Agents/?snr=1_7_7_240_150_1",
  "Secret Santa": "https://store.steampowered.com/app/500690/Secret_Santa/?snr=1_7_7_240_150_1",
  "Of Guards and Thieves - Firefight": "https://store.steampowered.com/app/598390/Of_Guards_and_Thieves__Firefight/?snr=1_7_7_240_150_1",
  "Prison Simulator Prologue": "https://store.steampowered.com/app/1431610/Prison_Simulator_Prologue/?snr=1_7_7_240_150_1",
  "Beyond Hanwell Teaser: The Royal Hallamshire": "https://store.steampowered.com/app/2573320/Beyond_Hanwell_Teaser_The_Royal_Hallamshire/?snr=1_7_7_240_150_1",
  "Yujiro's Mansion": "https://store.steampowered.com/app/2548070/Yujiros_Mansion/?snr=1_7_7_240_150_1",
  "CATASS": "https://store.steampowered.com/app/2430220/CATASS/?snr=1_7_7_240_150_1",
  "Just Act Natural": "https://store.steampowered.com/app/1485080/Just_Act_Natural/?snr=1_7_7_240_150_1",
  "Puppet Master: The Game": "https://store.steampowered.com/app/1757610/Puppet_Master_The_Game/?snr=1_7_7_240_150_1",
  "Aragami - Assassin Masks Set": "https://store.steampowered.com/app/564400/Aragami__Assassin_Masks_Set/?snr=1_7_7_240_150_1",
  "Public Enemy: Revolution Simulator": "https://store.steampowered.com/app/1125870/Public_Enemy_Revolution_Simulator/?snr=1_7_7_240_150_1",
  "Albert and Camille's Little Lille Adventure": "https://store.steampowered.com/app/1804580/Albert_and_Camilles_Little_Lille_Adventure/?snr=1_7_7_240_150_1",
  "Five Nights at Freddy's: Security Breach - Ruin": "https://store.steampowered.com/app/1924720/Five_Nights_at_Freddys_Security_Breach__Ruin/?snr=1_7_7_240_150_1",
  "Siege Survival: Gloria Victis Prologue": "https://store.steampowered.com/app/1362420/Siege_Survival_Gloria_Victis_Prologue/?snr=1_7_7_240_150_1",
  "Hello Guest: Hello Neighbor 2 pre-alpha": "https://store.steampowered.com/app/1504150/Hello_Guest_Hello_Neighbor_2_prealpha/?snr=1_7_7_240_150_1",
  "The Backroom - Lost and Found": "https://store.steampowered.com/app/2019830/The_Backroom__Lost_and_Found/?snr=1_7_7_240_150_1"
}