{
  "Paper Lily - Chapter 1": "https://store.steampowered.com/app/2220360/Paper_Lily__Chapter_1/?snr=1_7_7_240_150_1",
  "Project Kat - Paper Lily Prologue": "https://store.steampowered.com/app/1698960/Project_Kat__Paper_Lily_Prologue/?snr=1_7_7_240_150_1",
  "DFHack - Dwarf Fortress Modding Engine": "https://store.steampowered.com/app/2346660/DFHack__Dwarf_Fortress_Modding_Engine/?snr=1_7_7_240_150_1",
  "VPet-Simulator": "https://store.steampowered.com/app/1920960/VPetSimulator/?snr=1_7_7_240_150_1",
  "The Chronicles Of Myrtana: Archolos": "https://store.steampowered.com/app/1467450/The_Chronicles_Of_Myrtana_Archolos/?snr=1_7_7_240_150_1",
  "Grimm's Hollow": "https://store.steampowered.com/app/1170880/Grimms_Hollow/?snr=1_7_7_240_150_1",
  "Magic Archery": "https://store.steampowered.com/app/2905170/Magic_Archery/?snr=1_7_7_240_150_1",
  "Illusion Carnival": "https://store.steampowered.com/app/2796340/Illusion_Carnival/?snr=1_7_7_240_150_1",
  "BLACK BOX LSS - The Shining Immortal": "https://store.steampowered.com/app/2434340/BLACK_BOX_LSS__The_Shining_Immortal/?snr=1_7_7_240_150_1",
  "DAVE THE DIVER - DREDGE Content Pack": "https://store.steampowered.com/app/2677020/DAVE_THE_DIVER__DREDGE_Content_Pack/?snr=1_7_7_240_150_1",
  "Black Gunner Wukong: Prologue": "https://store.steampowered.com/app/2095890/Black_Gunner_Wukong_Prologue/?snr=1_7_7_240_150_1",
  "The Test: Secrets of the Soul 2": "https://store.steampowered.com/app/2349550/The_Test_Secrets_of_the_Soul_2/?snr=1_7_7_240_150_1",
  "tModLoader": "https://store.steampowered.com/app/1281930/tModLoader/?snr=1_7_7_240_150_1",
  "Outcore: Desktop Adventure": "https://store.steampowered.com/app/1275670/Outcore_Desktop_Adventure/?snr=1_7_7_240_150_1",
  "Eternal Senia": "https://store.steampowered.com/app/351640/Eternal_Senia/?snr=1_7_7_240_150_1",
  "At Home Alone Final": "https://store.steampowered.com/app/1740100/At_Home_Alone_Final/?snr=1_7_7_240_150_1",
  "Downfall - A Slay the Spire Fan Expansion": "https://store.steampowered.com/app/1865780/Downfall__A_Slay_the_Spire_Fan_Expansion/?snr=1_7_7_240_150_1",
  "Princess Remedy in a World of Hurt": "https://store.steampowered.com/app/407900/Princess_Remedy_in_a_World_of_Hurt/?snr=1_7_7_240_150_1",
  "Pages of Time: Prologue": "https://store.steampowered.com/app/2207540/Pages_of_Time_Prologue/?snr=1_7_7_240_150_1",
  "Hello Charlotte EP2: Requiem Aeternam Deo": "https://store.steampowered.com/app/557630/Hello_Charlotte_EP2_Requiem_Aeternam_Deo/?snr=1_7_7_240_150_1",
  "The Test: Secrets of the Soul": "https://store.steampowered.com/app/2231890/The_Test_Secrets_of_the_Soul/?snr=1_7_7_240_150_1",
  "My Sticker Book": "https://store.steampowered.com/app/2088270/My_Sticker_Book/?snr=1_7_7_240_150_1",
  "Skyrim Script Extender (SKSE)": "https://store.steampowered.com/app/365720/Skyrim_Script_Extender_SKSE/?snr=1_7_7_240_150_1",
  "永冻之壳 The Shell of Permafrost": "https://store.steampowered.com/app/976940/_The_Shell_of_Permafrost/?snr=1_7_7_240_150_1",
  "Shogun Showdown: Prologue": "https://store.steampowered.com/app/2316330/Shogun_Showdown_Prologue/?snr=1_7_7_240_150_1",
  "Dying Light Original Soundtrack": "https://store.steampowered.com/app/798540/Dying_Light_Original_Soundtrack/?snr=1_7_7_240_150_1",
  "NieR Replicant 4 YoRHa": "https://store.steampowered.com/app/1408390/NieR_Replicant_4_YoRHa/?snr=1_7_7_240_150_1",
  "Tails Noir: Prologue": "https://store.steampowered.com/app/992310/Tails_Noir_Prologue/?snr=1_7_7_240_150_1",
  "Duck Simulator 2": "https://store.steampowered.com/app/1808800/Duck_Simulator_2/?snr=1_7_7_240_150_1",
  "Trick &amp; Treat": "https://store.steampowered.com/app/497640/Trick__Treat/?snr=1_7_7_240_150_1",
  "Epic Battle Fantasy 3": "https://store.steampowered.com/app/521200/Epic_Battle_Fantasy_3/?snr=1_7_7_240_150_1",
  "Moonring": "https://store.steampowered.com/app/2373630/Moonring/?snr=1_7_7_240_150_1",
  "The Life and Suffering of Sir Brante — Chapter 1&amp;2": "https://store.steampowered.com/app/1460090/The_Life_and_Suffering_of_Sir_Brante__Chapter_12/?snr=1_7_7_240_150_1",
  "Unheard - The Lethal Script（致命剧本）": "https://store.steampowered.com/app/1065280/Unheard__The_Lethal_Script/?snr=1_7_7_240_150_1",
  "Escape from Ever After: Onboarding": "https://store.steampowered.com/app/2789420/Escape_from_Ever_After_Onboarding/?snr=1_7_7_240_150_1",
  "Vampire Survivors: Emerald Diorama": "https://store.steampowered.com/app/3451100/Vampire_Survivors_Emerald_Diorama/?snr=1_7_7_240_150_1",
  "Draw": "https://store.steampowered.com/app/2473980/Draw/?snr=1_7_7_240_150_1",
  "Dying Light – L4D2 Bill and Gnome Chompski Pack": "https://store.steampowered.com/app/1454750/Dying_Light__L4D2_Bill_and_Gnome_Chompski_Pack/?snr=1_7_7_240_150_1",
  "Dying Light - Ox Warrior Bundle": "https://store.steampowered.com/app/1524890/Dying_Light__Ox_Warrior_Bundle/?snr=1_7_7_240_150_1",
  "NIGHT-RUNNERS™ PROLOGUE": "https://store.steampowered.com/app/2707900/NIGHTRUNNERS_PROLOGUE/?snr=1_7_7_240_150_1",
  "NGU IDLE": "https://store.steampowered.com/app/1147690/NGU_IDLE/?snr=1_7_7_240_150_1",
  "Farmer Against Potatoes Idle": "https://store.steampowered.com/app/1535560/Farmer_Against_Potatoes_Idle/?snr=1_7_7_240_150_1",
  "Bitburner": "https://store.steampowered.com/app/1812820/Bitburner/?snr=1_7_7_240_150_1",
  "The Riftbreaker: Prologue": "https://store.steampowered.com/app/1293860/The_Riftbreaker_Prologue/?snr=1_7_7_240_150_1",
  "Saihate Station": "https://store.steampowered.com/app/3079280/Saihate_Station/?snr=1_7_7_240_150_1",
  "OH MY GOD, LOOK AT THIS KNIGHT": "https://store.steampowered.com/app/781440/OH_MY_GOD_LOOK_AT_THIS_KNIGHT/?snr=1_7_7_240_150_1",
  "There is No GreenDam": "https://store.steampowered.com/app/1109460/There_is_No_GreenDam/?snr=1_7_7_240_150_1",
  "The Witcher 3: Wild Hunt - New Finisher Animations": "https://store.steampowered.com/app/378646/The_Witcher_3_Wild_Hunt__New_Finisher_Animations/?snr=1_7_7_240_150_1",
  "重生之我是小虾米": "https://store.steampowered.com/app/3101720/_/?snr=1_7_7_240_150_1",
  "The Lar": "https://store.steampowered.com/app/1084570/The_Lar/?snr=1_7_7_240_150_1"
}