{
  "Dungeon Tycoon: Prologue": "https://store.steampowered.com/app/3090980/Dungeon_Tycoon_Prologue/?snr=1_7_7_240_150_1",
  "TM - Prologue": "https://store.steampowered.com/app/1614730/TM__Prologue/?snr=1_7_7_240_150_1",
  "RPG Sounds": "https://store.steampowered.com/app/1480140/RPG_Sounds/?snr=1_7_7_240_150_1",
  "The RPG Engine": "https://store.steampowered.com/app/1818180/The_RPG_Engine/?snr=1_7_7_240_150_1",
  "Fighting Fantasy Classics": "https://store.steampowered.com/app/856880/Fighting_Fantasy_Classics/?snr=1_7_7_240_150_1",
  "Game Master Engine": "https://store.steampowered.com/app/1451680/Game_Master_Engine/?snr=1_7_7_240_150_1",
  "Sands of Slumber: The RPG": "https://store.steampowered.com/app/2174160/Sands_of_Slumber_The_RPG/?snr=1_7_7_240_150_1",
  "Last Blossom: Roleplaying tabletop based scene": "https://store.steampowered.com/app/1604690/Last_Blossom_Roleplaying_tabletop_based_scene/?snr=1_7_7_240_150_1",
  "The Red Prison": "https://store.steampowered.com/app/1074040/The_Red_Prison/?snr=1_7_7_240_150_1",
  "The Complex IV": "https://store.steampowered.com/app/2460770/The_Complex_IV/?snr=1_7_7_240_150_1",
  "Digital TableTops Player": "https://store.steampowered.com/app/3073720/Digital_TableTops_Player/?snr=1_7_7_240_150_1",
  "Neverwinter": "https://store.steampowered.com/app/109600/Neverwinter/?snr=1_7_7_240_150_1",
  "Idle Champions of the Forgotten Realms": "https://store.steampowered.com/app/627690/Idle_Champions_of_the_Forgotten_Realms/?snr=1_7_7_240_150_1",
  "Tales of Fablecraft": "https://store.steampowered.com/app/2176900/Tales_of_Fablecraft/?snr=1_7_7_240_150_1",
  "Write Warz": "https://store.steampowered.com/app/2477650/Write_Warz/?snr=1_7_7_240_150_1",
  "Vagrus - The Riven Realms: Demo (Prologue)": "https://store.steampowered.com/app/1304660/Vagrus__The_Riven_Realms_Demo_Prologue/?snr=1_7_7_240_150_1",
  "Wildshape - Map Editor (free demo)": "https://store.steampowered.com/app/1543590/Wildshape__Map_Editor_free_demo/?snr=1_7_7_240_150_1",
  "Dungeons &amp; Dragons Online®": "https://store.steampowered.com/app/206480/Dungeons__Dragons_Online/?snr=1_7_7_240_150_1",
  "Underlight": "https://store.steampowered.com/app/980730/Underlight/?snr=1_7_7_240_150_1"
}