{
  "Paper Lily - Chapter 1": "https://store.steampowered.com/app/2220360/Paper_Lily__Chapter_1/?snr=1_7_7_240_150_1",
  "Project Kat - Paper Lily Prologue": "https://store.steampowered.com/app/1698960/Project_Kat__Paper_Lily_Prologue/?snr=1_7_7_240_150_1",
  "Poco": "https://store.steampowered.com/app/3454610/Poco/?snr=1_7_7_240_150_1",
  "ENA: Dream BBQ": "https://store.steampowered.com/app/2134320/ENA_Dream_BBQ/?snr=1_7_7_240_150_1",
  "Sheepy: A Short Adventure": "https://store.steampowered.com/app/1568400/Sheepy_A_Short_Adventure/?snr=1_7_7_240_150_1",
  "Grimm's Hollow": "https://store.steampowered.com/app/1170880/Grimms_Hollow/?snr=1_7_7_240_150_1",
  "Our Life: Beginnings &amp; Always": "https://store.steampowered.com/app/1129190/Our_Life_Beginnings__Always/?snr=1_7_7_240_150_1",
  "A Date with Death": "https://store.steampowered.com/app/2415010/A_Date_with_Death/?snr=1_7_7_240_150_1",
  "Purrgatory": "https://store.steampowered.com/app/1713610/Purrgatory/?snr=1_7_7_240_150_1",
  "Katawa Shoujo": "https://store.steampowered.com/app/3068300/Katawa_Shoujo/?snr=1_7_7_240_150_1",
  "Homicipher: Demo": "https://store.steampowered.com/app/2423320/Homicipher_Demo/?snr=1_7_7_240_150_1",
  "I Frog-ot": "https://store.steampowered.com/app/2226870/I_Frogot/?snr=1_7_7_240_150_1",
  "The Test: Secrets of the Soul 2": "https://store.steampowered.com/app/2349550/The_Test_Secrets_of_the_Soul_2/?snr=1_7_7_240_150_1",
  "Eternal Senia": "https://store.steampowered.com/app/351640/Eternal_Senia/?snr=1_7_7_240_150_1",
  "At Home Alone Final": "https://store.steampowered.com/app/1740100/At_Home_Alone_Final/?snr=1_7_7_240_150_1",
  "Princess Remedy in a World of Hurt": "https://store.steampowered.com/app/407900/Princess_Remedy_in_a_World_of_Hurt/?snr=1_7_7_240_150_1",
  "Lily's Well": "https://store.steampowered.com/app/1834870/Lilys_Well/?snr=1_7_7_240_150_1",
  "Hello Charlotte EP2: Requiem Aeternam Deo": "https://store.steampowered.com/app/557630/Hello_Charlotte_EP2_Requiem_Aeternam_Deo/?snr=1_7_7_240_150_1",
  "The Test: Secrets of the Soul": "https://store.steampowered.com/app/2231890/The_Test_Secrets_of_the_Soul/?snr=1_7_7_240_150_1",
  "Jerma's Big Adventure": "https://store.steampowered.com/app/1722570/Jermas_Big_Adventure/?snr=1_7_7_240_150_1",
  "PockeDate! - Pocket Dating Simulator": "https://store.steampowered.com/app/3107350/PockeDate__Pocket_Dating_Simulator/?snr=1_7_7_240_150_1",
  "My succubus Kukula": "https://store.steampowered.com/app/2848420/My_succubus_Kukula/?snr=1_7_7_240_150_1",
  "Life is Strange - Episode 1": "https://store.steampowered.com/app/319630/Life_is_Strange__Episode_1/?snr=1_7_7_240_150_1",
  "Nightmare Kart": "https://store.steampowered.com/app/2930160/Nightmare_Kart/?snr=1_7_7_240_150_1",
  "Meteor 60 Seconds!": "https://store.steampowered.com/app/788770/Meteor_60_Seconds/?snr=1_7_7_240_150_1",
  "Cinderella Phenomenon - Otome/Visual Novel": "https://store.steampowered.com/app/568770/Cinderella_Phenomenon__OtomeVisual_Novel/?snr=1_7_7_240_150_1",
  "Mitoza": "https://store.steampowered.com/app/1516240/Mitoza/?snr=1_7_7_240_150_1",
  "Moonring": "https://store.steampowered.com/app/2373630/Moonring/?snr=1_7_7_240_150_1",
  "The Life and Suffering of Sir Brante — Chapter 1&amp;2": "https://store.steampowered.com/app/1460090/The_Life_and_Suffering_of_Sir_Brante__Chapter_12/?snr=1_7_7_240_150_1",
  "Children of Silentown: Prologue": "https://store.steampowered.com/app/1451740/Children_of_Silentown_Prologue/?snr=1_7_7_240_150_1",
  "Escape from Ever After: Onboarding": "https://store.steampowered.com/app/2789420/Escape_from_Ever_After_Onboarding/?snr=1_7_7_240_150_1",
  "MetaWare High School (Demo)": "https://store.steampowered.com/app/1194740/MetaWare_High_School_Demo/?snr=1_7_7_240_150_1",
  "Gooba Ball": "https://store.steampowered.com/app/2878140/Gooba_Ball/?snr=1_7_7_240_150_1",
  "HackHub: Free Trial": "https://store.steampowered.com/app/3022810/HackHub_Free_Trial/?snr=1_7_7_240_150_1",
  "How Fish Is Made": "https://store.steampowered.com/app/1854430/How_Fish_Is_Made/?snr=1_7_7_240_150_1",
  "one night, hot springs": "https://store.steampowered.com/app/917680/one_night_hot_springs/?snr=1_7_7_240_150_1",
  "Saihate Station": "https://store.steampowered.com/app/3079280/Saihate_Station/?snr=1_7_7_240_150_1",
  "重生之我是小虾米": "https://store.steampowered.com/app/3101720/_/?snr=1_7_7_240_150_1",
  "It gets so lonely here": "https://store.steampowered.com/app/2386250/It_gets_so_lonely_here/?snr=1_7_7_240_150_1",
  "High Entropy: Challenges": "https://store.steampowered.com/app/1389630/High_Entropy_Challenges/?snr=1_7_7_240_150_1",
  "Liquidators": "https://store.steampowered.com/app/1382200/Liquidators/?snr=1_7_7_240_150_1",
  "Absent in the Rain": "https://store.steampowered.com/app/2168610/Absent_in_the_Rain/?snr=1_7_7_240_150_1",
  "Lake of Voices": "https://store.steampowered.com/app/782340/Lake_of_Voices/?snr=1_7_7_240_150_1",
  "The Thief, the Witch, the Toad, and the Mushroom.": "https://store.steampowered.com/app/2233770/The_Thief_the_Witch_the_Toad_and_the_Mushroom/?snr=1_7_7_240_150_1",
  "One's Own Exile": "https://store.steampowered.com/app/3086720/Ones_Own_Exile/?snr=1_7_7_240_150_1",
  "Hexed Time": "https://store.steampowered.com/app/3278590/Hexed_Time/?snr=1_7_7_240_150_1",
  "Graveyard Girls": "https://store.steampowered.com/app/2055540/Graveyard_Girls/?snr=1_7_7_240_150_1",
  "Berry": "https://store.steampowered.com/app/1823370/Berry/?snr=1_7_7_240_150_1",
  "Love Alone Death": "https://store.steampowered.com/app/2627030/Love_Alone_Death/?snr=1_7_7_240_150_1",
  "Cursed 3": "https://store.steampowered.com/app/2110460/Cursed_3/?snr=1_7_7_240_150_1"
}